LICENSE
MANIFEST.in
README.md
setup.py
django_skebby/__init__.py
django_skebby/models.py
django_skebby/tests.py
django_skebby/urls.py
django_skebby/utils.py
django_skebby/views.py
django_skebby.egg-info/PKG-INFO
django_skebby.egg-info/SOURCES.txt
django_skebby.egg-info/dependency_links.txt
django_skebby.egg-info/not-zip-safe
django_skebby.egg-info/pbr.json
django_skebby.egg-info/requires.txt
django_skebby.egg-info/top_level.txt