Metadata-Version: 1.1
Name: django-skebby
Version: 0.3.1
Summary: A Django app to send sms with skebby
Home-page: https://github.com/xrmx/django-skebby
Author: Riccardo Magliocchetti
Author-email: riccardo.magliocchetti@gmail.com
License: BSD License
Platform: OS Independent
Classifier: Environment :: Web Environment
Classifier: Framework :: Django
Classifier: Intended Audience :: Developers
Classifier: License :: OSI Approved :: BSD License
Classifier: Operating System :: OS Independent
Classifier: Programming Language :: Python
Classifier: Topic :: Software Development :: Libraries :: Application Frameworks
Classifier: Topic :: Internet :: WWW/HTTP :: Dynamic Content
